tinytroupe/__init__.py
tinytroupe-0.0.1.dist-info/METADATA
tinytroupe-0.0.1.dist-info/WHEEL
tinytroupe-0.0.1.dist-info/top_level.txt
tinytroupe-0.0.1.dist-info/RECORD
