Metadata-Version: 2.1
Name: tinytroupe
Version: 0.0.1
Summary: This is a placeholder for the TinyTroupe library.
Home-page: https://github.com/microsoft/tinytroupe
Author: Paulo Salem
Author-email: paulo.salem@microsoft.com
Classifier: Programming Language :: Python :: 3
Classifier: License :: OSI Approved :: MIT License
Classifier: Operating System :: OS Independent
Requires-Python: >=3.10
